ipld_car/__init__.py
ipld_car-0.0.1.dist-info/METADATA
ipld_car-0.0.1.dist-info/WHEEL
ipld_car-0.0.1.dist-info/licenses/LICENSE.md
ipld_car-0.0.1.dist-info/RECORD
