Metadata-Version: 2.4
Name: ipld_car
Version: 0.0.1
Summary: Content Addressable aRchive format reader and writer.
Project-URL: Homepage, https://github.com/storacha/py-ipld-car
Project-URL: Issues, https://github.com/storacha/py-ipld-car/issues
Author-email: Alan Shaw <alan@storacha.network>
License-Expression: Apache-2.0 OR MIT
License-File: LICENSE.md
Classifier: Operating System :: OS Independent
Classifier: Programming Language :: Python :: 3
Requires-Python: >=3.9
